mcp_manager/__init__.py
mcp_manager/cli.py
mcp_manager/dependency_checker.py
mcp_manager/list_servers.py
mcp_manager/server_registry.py
mcp_manager/tests/__init__.py
mcp_manager/tests/__snapshots__/test_cli.ambr
mcp_manager/tests/test_cli.py
mcp_manager-0.2.6.dist-info/LICENSE
mcp_manager-0.2.6.dist-info/METADATA
mcp_manager-0.2.6.dist-info/WHEEL
mcp_manager-0.2.6.dist-info/entry_points.txt
mcp_manager-0.2.6.dist-info/RECORD
