Metadata-Version: 2.3
Name: mcp-manager
Version: 0.2.6
Summary: A CLI tool for managing Model Context Protocol (MCP) servers
License: GPL-3.0-or-later
Keywords: mcp,cli,server-management,ai-tools,claude,anthropic,browser-automation,playwright,ai-assistant,automation,developer-tools,llm-tools,claude-desktop,cursor-ide,claude-code,model-context-protocol,ai-integration,server-automation,development-tools,productivity
Author: Your Name
Author-email: your.email@example.com
Requires-Python: >=3.9,<4.0
Classifier: Development Status :: 4 - Beta
Classifier: Environment :: Console
Classifier: Intended Audience :: Developers
Classifier: License :: OSI Approved :: GNU General Public License v3 (GPLv3)
Classifier: License :: OSI Approved :: GNU General Public License v3 or later (GPLv3+)
Classifier: Operating System :: OS Independent
Classifier: Programming Language :: Python :: 3
Classifier: Programming Language :: Python :: 3.9
Classifier: Programming Language :: Python :: 3.10
Classifier: Programming Language :: Python :: 3.11
Classifier: Programming Language :: Python :: 3.12
Classifier: Programming Language :: Python :: 3.13
Classifier: Topic :: Software Development :: Libraries :: Python Modules
Classifier: Topic :: System :: Installation/Setup
Classifier: Topic :: Utilities
Requires-Dist: click (>=8.1.8,<9.0.0)
Requires-Dist: pydantic (>=2.6.1,<3.0.0)
Requires-Dist: rich (>=13.7.0,<14.0.0)
Requires-Dist: tabulate (>=0.9.0,<0.10.0)
Requires-Dist: typer (>=0.15.2,<0.16.0)
Project-URL: Homepage, https://github.com/nstebbins/mcp-manager
Project-URL: Repository, https://github.com/nstebbins/mcp-manager
